[
    {
        "lessons": [
            {
                "title": "Exploring Atomic Structure and the Periodic Table",
                "lecture": "In today's science lesson, we'll begin exploring atomic structure and the periodic table. This introduction will set a firm foundation for our studies this week. Let's start by discussing the structure of atoms.[p]\n\nAtoms are the basic building blocks of matter. Everything around us, including ourselves, is made up of atoms. Atoms consist of three main subatomic particles: protons, neutrons, and electrons. Protons are positively charged particles that are located in the nucleus, which is the very center of the atom. Neutrons, which have no charge, are also found in the nucleus alongside protons. Finally, we have electrons, which are negatively charged and orbit around the nucleus in specific regions called electron shells or energy levels.[p]\n\nThe number of protons in an atom determines what element it is. For example, hydrogen has one proton, whereas carbon has six protons. This unique arrangement is why each element has distinct chemical properties. The mass number of an atom is calculated by adding the number of protons and neutrons together.  Understanding this structure is essential because the behavior and reactions of atoms are heavily influenced by the arrangement and number of these subatomic particles.[p] \n\nNow, let\u2019s move on to our second subtopic: elements and compounds. An element is a substance that cannot be broken down into simpler substances by chemical means. Examples of elements include hydrogen, oxygen, and gold. Each element is represented in the periodic table by its unique symbol, like H for hydrogen and O for oxygen.[p] \n\nOn the other hand, when two or more elements combine chemically, they form a compound. Compounds have distinct properties that are very different from the elements that make them up. A common example is water (H2O), which is formed when two hydrogen atoms bond with one oxygen atom. Compounds can be made in various ways, including ionic and covalent bonds, which we'll explore in a later lesson, but just remember that the key difference is that compounds consist of two or more different elements combined together.[p]\n\nNext, we will discuss the periodic table layout. The periodic table is a systematic arrangement of all known elements, organized by their atomic number, electron configuration, and recurring chemical properties. Each row in the periodic table represents a period, and the elements within a period have the same number of electron shells.[p] \n\nThe elements are grouped into columns called groups or families. Elements in the same group have similar properties; for instance, the elements in Group 1, known as alkali metals, are highly reactive and have one electron in their outer shell.[p] Moreover, the periodic table is divided into metals, nonmetals, and metalloids, based on their properties. Metals, found on the left and in the center of the table, are generally good conductors of electricity and heat, while nonmetals, located on the right, tend to be poor conductors and more brittle. Understanding the layout of the periodic table is crucial for predicting the behavior of elements and their compounds in chemical reactions.[p] \n\nIn summary, we learned that atoms are the fundamental units of matter, made up of protons, neutrons, and electrons. We explored the difference between elements and compounds, recognizing that while elements are pure substances, compounds are combinations of different elements. We also discovered how elements are organized in the periodic table, which not only categorizes elements but also helps us understand their properties and relationships.[p] \n\nAs you continue to study atomic structure and the periodic table, keep in mind how this information will serve as a foundation for understanding chemistry as a whole. Paying close attention to the layout of the periodic table will make it easier to remember the elements and their characteristics, which will be beneficial in future studies. \n\nTo reinforce your understanding, you may refer to the following Wikipedia pages:\n1. Atomic Structure: https://en.wikipedia.org/wiki/Atomic_structure (Key: Atomic Structure)\n2. Element: https://en.wikipedia.org/wiki/Element (Key: Element)\n3. Compound: https://en.wikipedia.org/wiki/Compound_(chemistry) (Key: Compound)\n4. Periodic Table: https://en.wikipedia.org/wiki/Periodic_table (Key: Periodic Table)",
                "summary": "In today's lecture, we learned about the fundamental particles that make up atoms, how to distinguish between elements and compounds, and how the periodic table is organized. This knowledge will help us better understand chemical properties and reactions in future topics.",
                "subject": "Science",
                "main_topic": "Atomic Structure and the Periodic Table",
                "sub_topics": [
                    "Structure of atoms",
                    "Elements and compounds",
                    "Understanding the periodic table layout"
                ],
                "wikipedia_refrences": [
                    "https://en.wikipedia.org/wiki/Atomic_structure",
                    "https://en.wikipedia.org/wiki/Element",
                    "https://en.wikipedia.org/wiki/Compound_(chemistry)",
                    "https://en.wikipedia.org/wiki/Periodic_table"
                ]
            }
        ]
    }
]